yadu/__init__.py
yadu-0.1.0.dist-info/METADATA
yadu-0.1.0.dist-info/WHEEL
yadu-0.1.0.dist-info/top_level.txt
yadu-0.1.0.dist-info/RECORD
