Metadata-Version: 2.4
Name: yadu
Version: 0.1.0
Summary: A simple package that prints 'IOS DEVELOPER' when imported
Home-page: https://github.com/YadurajManu
Author: Yaduraj
Author-email: yadurajsingham@gmail.com
Classifier: Programming Language :: Python :: 3
Classifier: License :: OSI Approved :: MIT License
Classifier: Operating System :: OS Independent
Requires-Python: >=3.6
Dynamic: author
Dynamic: author-email
Dynamic: classifier
Dynamic: description
Dynamic: description-content-type
Dynamic: home-page
Dynamic: requires-python
Dynamic: summary
